Video2Pics/Video2Pics.py
Video2Pics/__init__.py
Video2Pics-0.0.1.dist-info/LICENSE
Video2Pics-0.0.1.dist-info/METADATA
Video2Pics-0.0.1.dist-info/WHEEL
Video2Pics-0.0.1.dist-info/top_level.txt
Video2Pics-0.0.1.dist-info/RECORD
