Metadata-Version: 2.1
Name: Video2Pics
Version: 0.0.1
Summary: Generate the pictures from the Video file
Home-page: https://github.com/premkumarkm/Video2Pics.git
Author: Prem Kumar KM
Author-email: premkumar_km@yahoo.co.in
License: UNKNOWN
Project-URL: Bug Tracker, https://github.com/premkumarkm/Video2Pics.git
Platform: UNKNOWN
Classifier: Programming Language :: Python :: 3
Classifier: License :: OSI Approved :: MIT License
Classifier: Operating System :: OS Independent
Requires-Python: >=3.6
